[
  {
    "team": "Denver Summit FC",
    "attackRating": 0.058,
    "defenseRating": 0.164,
    "overallRating": 0.111,
    "nMatches": 14,
    "currentRank": 1
  },
  {
    "team": "Chicago Stars FC",
    "attackRating": -0.287,
    "defenseRating": 0.483,
    "overallRating": 0.098,
    "nMatches": 41,
    "currentRank": 2
  },
  {
    "team": "Bay FC",
    "attackRating": 0.013,
    "defenseRating": 0.151,
    "overallRating": 0.082,
    "nMatches": 40,
    "currentRank": 3
  },
  {
    "team": "Houston Dash",
    "attackRating": -0.224,
    "defenseRating": 0.318,
    "overallRating": 0.047,
    "nMatches": 41,
    "currentRank": 4
  },
  {
    "team": "Kansas City Current",
    "attackRating": 0.259,
    "defenseRating": -0.2,
    "overallRating": 0.03,
    "nMatches": 41,
    "currentRank": 5
  },
  {
    "team": "Seattle Reign FC",
    "attackRating": -0.064,
    "defenseRating": 0.115,
    "overallRating": 0.026,
    "nMatches": 40,
    "currentRank": 6
  },
  {
    "team": "Portland Thorns FC",
    "attackRating": 0.024,
    "defenseRating": 0.01,
    "overallRating": 0.017,
    "nMatches": 42,
    "currentRank": 7
  },
  {
    "team": "Racing Louisville FC",
    "attackRating": -0.149,
    "defenseRating": 0.18,
    "overallRating": 0.016,
    "nMatches": 40,
    "currentRank": 8
  },
  {
    "team": "North Carolina Courage",
    "attackRating": 0.1,
    "defenseRating": -0.09,
    "overallRating": 0.005,
    "nMatches": 40,
    "currentRank": 9
  },
  {
    "team": "Boston Legacy FC",
    "attackRating": 0.046,
    "defenseRating": -0.055,
    "overallRating": -0.004,
    "nMatches": 16,
    "currentRank": 10
  },
  {
    "team": "Gotham FC",
    "attackRating": 0.059,
    "defenseRating": -0.094,
    "overallRating": -0.018,
    "nMatches": 41,
    "currentRank": 11
  },
  {
    "team": "San Diego Wave FC",
    "attackRating": 0.184,
    "defenseRating": -0.231,
    "overallRating": -0.024,
    "nMatches": 42,
    "currentRank": 12
  },
  {
    "team": "Utah Royals",
    "attackRating": 0.076,
    "defenseRating": -0.129,
    "overallRating": -0.026,
    "nMatches": 41,
    "currentRank": 13
  },
  {
    "team": "Angel City FC",
    "attackRating": 0.078,
    "defenseRating": -0.139,
    "overallRating": -0.03,
    "nMatches": 40,
    "currentRank": 14
  },
  {
    "team": "Washington Spirit",
    "attackRating": 0.004,
    "defenseRating": -0.277,
    "overallRating": -0.136,
    "nMatches": 41,
    "currentRank": 15
  },
  {
    "team": "Orlando Pride",
    "attackRating": -0.175,
    "defenseRating": -0.157,
    "overallRating": -0.166,
    "nMatches": 42,
    "currentRank": 16
  }
]